LICENSE
MANIFEST.in
ReadMe.md
setup.py
Spanve/Spanve_cli.py
Spanve/__init__.py
Spanve/cluster.py
Spanve/utils.py
Spanve.egg-info/PKG-INFO
Spanve.egg-info/SOURCES.txt
Spanve.egg-info/dependency_links.txt
Spanve.egg-info/entry_points.txt
Spanve.egg-info/requires.txt
Spanve.egg-info/top_level.txt