Metadata-Version: 2.1
Name: Spanve
Version: 0.1.6
Summary: Spatial Neighborhood Variably Expressed Genes (Spanve) is a method for detecting spatial variably expressed genes in spatial transcriptomics data.
Home-page: https://github.com/gx-Cai/Spanve
Author: gx.Cai
License-File: LICENSE
